Metadata-Version: 1.0
Name: rpaste
Version: 0.1.0
Summary: Code Snippets Uploader
Home-page: https://github.com/rpaste/rpaste
Author: Anup Pokhrel
Author-email: virtualanup@gmail.com
License: UNKNOWN
Keywords: rpaste,paste,bin
Platform: UNKNOWN
